radiacode/__init__.py
radiacode/bytes_buffer.py
radiacode/decoders/__init__.py
radiacode/decoders/databuf.py
radiacode/decoders/spectrum.py
radiacode/radiacode.py
radiacode/transports/__init__.py
radiacode/transports/bluetooth.py
radiacode/transports/usb.py
radiacode/types.py
radiacode-0.3.5.dist-info/LICENSE
radiacode-0.3.5.dist-info/METADATA
radiacode-0.3.5.dist-info/WHEEL
radiacode-0.3.5.dist-info/RECORD
