Metadata-Version: 2.3
Name: radiacode
Version: 0.3.5
Summary: Library for RadiaCode-101
License: MIT
Author: Maxim Andreev
Author-email: andreevmaxim@gmail.com
Requires-Python: >=3.9,<4.0
Classifier: Development Status :: 3 - Alpha
Classifier: License :: OSI Approved :: MIT License
Classifier: Programming Language :: Python :: 3
Classifier: Programming Language :: Python :: 3.9
Classifier: Programming Language :: Python :: 3.10
Classifier: Programming Language :: Python :: 3.11
Classifier: Programming Language :: Python :: 3.12
Classifier: Programming Language :: Python :: 3.13
Classifier: Programming Language :: Python :: 3 :: Only
Provides-Extra: examples
Requires-Dist: aiohttp (>=3.9,<4.0) ; extra == "examples"
Requires-Dist: bluepy (>=1.3,<2.0) ; sys_platform == "linux"
Requires-Dist: matplotlib (>=3.7,<4.0) ; extra == "examples"
Requires-Dist: numpy (>=1.26,<2.0) ; extra == "examples"
Requires-Dist: prometheus-client (>=0.19,<0.20) ; extra == "examples"
Requires-Dist: pyusb (>=1.3,<2.0)
Requires-Dist: pyyaml (>=6.0,<7.0) ; extra == "examples"
Project-URL: Repository, https://github.com/cdump/radiacode
